cytonormpy/__init__.py
cytonormpy/_clustering/__init__.py
cytonormpy/_clustering/_cluster_algorithms.py
cytonormpy/_cytonorm/__init__.py
cytonormpy/_cytonorm/_cytonorm.py
cytonormpy/_cytonorm/_examples.py
cytonormpy/_cytonorm/_utils.py
cytonormpy/_dataset/__init__.py
cytonormpy/_dataset/_dataprovider.py
cytonormpy/_dataset/_datareader.py
cytonormpy/_dataset/_dataset.py
cytonormpy/_dataset/_fcs_file.py
cytonormpy/_dataset/_metadata.py
cytonormpy/_evaluation/__init__.py
cytonormpy/_evaluation/_emd.py
cytonormpy/_evaluation/_emd_utils.py
cytonormpy/_evaluation/_mad.py
cytonormpy/_evaluation/_mad_utils.py
cytonormpy/_evaluation/_utils.py
cytonormpy/_normalization/__init__.py
cytonormpy/_normalization/_quantile_calc.py
cytonormpy/_normalization/_spline_calc.py
cytonormpy/_normalization/_utils.py
cytonormpy/_plotting/__init__.py
cytonormpy/_plotting/_cv_heatmap.py
cytonormpy/_plotting/_evaluations.py
cytonormpy/_plotting/_histogram.py
cytonormpy/_plotting/_plotter.py
cytonormpy/_plotting/_scatter.py
cytonormpy/_plotting/_splineplot.py
cytonormpy/_plotting/_utils.py
cytonormpy/_resources/Gates_PTLG021_Unstim_Control_1.fcs
cytonormpy/_resources/Gates_PTLG021_Unstim_Control_2.fcs
cytonormpy/_resources/Gates_PTLG028_Unstim_Control_1.fcs
cytonormpy/_resources/Gates_PTLG028_Unstim_Control_2.fcs
cytonormpy/_resources/Gates_PTLG034_Unstim_Control_1.fcs
cytonormpy/_resources/Gates_PTLG034_Unstim_Control_2.fcs
cytonormpy/_resources/Gates_PTLG034_Unstim_Control_2_dup.fcs
cytonormpy/_resources/Norm_Gates_PTLG021_Unstim_Control_2.fcs
cytonormpy/_resources/Norm_Gates_PTLG028_Unstim_Control_2.fcs
cytonormpy/_resources/Norm_Gates_PTLG034_Unstim_Control_2.fcs
cytonormpy/_resources/coding_detectors.txt
cytonormpy/_resources/metadata.csv
cytonormpy/_resources/metadata.xlsx
cytonormpy/_resources/metadata_sid.csv
cytonormpy/_resources/test_adata.h5ad
cytonormpy/_transformation/__init__.py
cytonormpy/_transformation/_transformations.py
cytonormpy/_utils/__init__.py
cytonormpy/_utils/_utils.py
cytonormpy-1.0.2.dist-info/METADATA
cytonormpy-1.0.2.dist-info/WHEEL
cytonormpy-1.0.2.dist-info/licenses/LICENSE
cytonormpy-1.0.2.dist-info/RECORD
