Metadata-Version: 2.4
Name: cytonormpy
Version: 1.0.2
Summary: CytoNorm for python
Project-URL: Homepage, http://github.com/TarikExner/CytoNormPy/
Project-URL: Bugtracker, http://github.com/TarikExner/CytoNormPy/
Author-email: Tarik Exner <Tarik.Exner@med.uni-heidelberg.de>
License-File: LICENSE
Keywords: batch,cytometry,cytonorm
Classifier: License :: OSI Approved :: MIT License
Classifier: Operating System :: OS Independent
Classifier: Programming Language :: Python :: 3
Requires-Python: >=3.9
Requires-Dist: anndata
Requires-Dist: flowio<=1.3.0
Requires-Dist: flowsom
Requires-Dist: flowutils
Requires-Dist: pandas>=2.0.0
Requires-Dist: pytometry
Provides-Extra: docs
Requires-Dist: docutils<=0.20; extra == 'docs'
Requires-Dist: ipython; extra == 'docs'
Requires-Dist: myst-parser; extra == 'docs'
Requires-Dist: nbsphinx; extra == 'docs'
Requires-Dist: nbsphinx-link; extra == 'docs'
Requires-Dist: pandoc; extra == 'docs'
Requires-Dist: sphinx-autodoc-typehints; extra == 'docs'
Requires-Dist: sphinx-book-theme>=1.0.0; extra == 'docs'
Requires-Dist: sphinx<=7.4; extra == 'docs'
Requires-Dist: sphinxcontrib-bibtex>=1.0.0; extra == 'docs'
Provides-Extra: test
Requires-Dist: pytest; extra == 'test'
Requires-Dist: pytest-cov; extra == 'test'
